unify_idents/__init__.py
unify_idents/unify.py
unify_idents/utils.py
unify_idents/engine_parsers/__init__.py
unify_idents/engine_parsers/base_parser.py
unify_idents/engine_parsers/ident/__init__.py
unify_idents/engine_parsers/ident/comet_2020_01_4_parser.py
unify_idents/engine_parsers/ident/dummy_parser.py
unify_idents/engine_parsers/ident/mascot_2_6_2_parser.py
unify_idents/engine_parsers/ident/msamanda_2_parser.py
unify_idents/engine_parsers/ident/msfragger_3_parser.py
unify_idents/engine_parsers/ident/msgfplus_2021_03_22_parser.py
unify_idents/engine_parsers/ident/omssa_2_1_9_parser.py
unify_idents/engine_parsers/ident/xtandem_alanine.py
unify_idents/engine_parsers/quant/__init__.py
unify_idents/engine_parsers/quant/flash_lfq_1_2_0_parser.py
unify_idents-1.6.1.dist-info/AUTHORS.TXT
unify_idents-1.6.1.dist-info/LICENSE
unify_idents-1.6.1.dist-info/METADATA
unify_idents-1.6.1.dist-info/WHEEL
unify_idents-1.6.1.dist-info/top_level.txt
unify_idents-1.6.1.dist-info/RECORD
